rectangle_packer-2.0.5.dist-info/licenses/LICENSE.md
rpack/__init__.py
rpack/_core.cp310-win_amd64.pyd
rpack/_core.pxd
rpack/_core.pyx
rpack/_rpack.cp310-win_amd64.pyd
rectangle_packer-2.0.5.dist-info/METADATA
rectangle_packer-2.0.5.dist-info/WHEEL
rectangle_packer-2.0.5.dist-info/top_level.txt
rectangle_packer-2.0.5.dist-info/RECORD
